src/__init__.py
src/commands.py
src/config.py
src/devtool.py
src/highlight.py
src/install.py
src/log.py
src/project.py
src/util.py
refl-0.1.dist-info/LICENSE
refl-0.1.dist-info/METADATA
refl-0.1.dist-info/WHEEL
refl-0.1.dist-info/top_level.txt
refl-0.1.dist-info/RECORD
